Metadata-Version: 2.1
Name: practice-problems-builder-ktraff
Version: 0.0.14
Summary: CLI tool for building practice programming problems
Home-page: https://github.com/ktraff/practice-problems-builder
Author: Kyle Traff
Author-email: ktraff@gmail.com
License: MIT
Platform: UNKNOWN
Classifier: Programming Language :: Python :: 3
Classifier: Programming Language :: Python :: 3.7
Classifier: License :: OSI Approved :: MIT License
Classifier: Operating System :: OS Independent
Requires-Python: >=3.7
Requires-Dist: jinja2
Requires-Dist: PyYAML
